fluxcloud/__init__.py
fluxcloud/defaults.py
fluxcloud/logger.py
fluxcloud/settings.yml
fluxcloud/version.py
fluxcloud/client/__init__.py
fluxcloud/client/apply.py
fluxcloud/client/config.py
fluxcloud/client/down.py
fluxcloud/client/experiment.py
fluxcloud/client/helpers.py
fluxcloud/client/listing.py
fluxcloud/client/run.py
fluxcloud/client/shell.py
fluxcloud/client/up.py
fluxcloud/main/__init__.py
fluxcloud/main/api.py
fluxcloud/main/client.py
fluxcloud/main/decorator.py
fluxcloud/main/experiment.py
fluxcloud/main/schemas.py
fluxcloud/main/settings.py
fluxcloud/main/template.py
fluxcloud/main/clouds/__init__.py
fluxcloud/main/clouds/templates.py
fluxcloud/main/clouds/aws/__init__.py
fluxcloud/main/clouds/aws/client.py
fluxcloud/main/clouds/aws/scripts/cluster-create
fluxcloud/main/clouds/aws/scripts/cluster-destroy
fluxcloud/main/clouds/aws/templates/cluster-config.yaml
fluxcloud/main/clouds/google/__init__.py
fluxcloud/main/clouds/google/client.py
fluxcloud/main/clouds/google/scripts/cluster-create
fluxcloud/main/clouds/google/scripts/cluster-destroy
fluxcloud/main/clouds/local/__init__.py
fluxcloud/main/clouds/local/minikube.py
fluxcloud/main/clouds/local/scripts/cluster-create-minikube
fluxcloud/main/clouds/local/scripts/cluster-destroy-minikube
fluxcloud/main/clouds/shared/__init__.py
fluxcloud/main/clouds/shared/scripts/helpers.sh
fluxcloud/tests/__init__.py
fluxcloud/tests/helpers.py
fluxcloud/tests/test_examples.py
fluxcloud/tests/test_settings.py
fluxcloud/tests/test_utils.py
fluxcloud/utils/__init__.py
fluxcloud/utils/fileio.py
fluxcloud/utils/misc.py
fluxcloud/utils/terminal.py
flux_cloud-0.2.1.dist-info/LICENSE
flux_cloud-0.2.1.dist-info/METADATA
flux_cloud-0.2.1.dist-info/NOTICE
flux_cloud-0.2.1.dist-info/WHEEL
flux_cloud-0.2.1.dist-info/entry_points.txt
flux_cloud-0.2.1.dist-info/top_level.txt
flux_cloud-0.2.1.dist-info/RECORD
