Metadata-Version: 2.1
Name: flux-cloud
Version: 0.2.1
Summary: deploy workflows to the flux operator in the cloud! 📦️
Home-page: https://github.com/converged-computing/flux-cloud
Author: Vanessa Sochat
Author-email: vsoch@users.noreply.github.com
Maintainer: Vanessa Sochat
License: LICENSE
Keywords: cloud,flux,deployment
Classifier: Intended Audience :: Science/Research
Classifier: Intended Audience :: Developers
Classifier: License :: OSI Approved :: MIT License
Classifier: Programming Language :: Python
Classifier: Topic :: Software Development
Classifier: Topic :: Scientific/Engineering
Classifier: Operating System :: Unix
Classifier: Programming Language :: Python :: 3.8
License-File: LICENSE
License-File: NOTICE
Requires-Dist: kubernetes
Requires-Dist: fluxoperator (>=0.0.19)
Requires-Dist: ruamel.yaml
Requires-Dist: jsonschema
Requires-Dist: requests
Requires-Dist: jinja2
Requires-Dist: flux-restful-client
Provides-Extra: all
Requires-Dist: kubernetes ; extra == 'all'
Requires-Dist: fluxoperator (>=0.0.19) ; extra == 'all'
Requires-Dist: ruamel.yaml ; extra == 'all'
Requires-Dist: jsonschema ; extra == 'all'
Requires-Dist: requests ; extra == 'all'
Requires-Dist: jinja2 ; extra == 'all'
Requires-Dist: flux-restful-client ; extra == 'all'
Requires-Dist: pytest (>=4.6.2) ; extra == 'all'
